zocalo_dls/__init__.py
zocalo_dls/service/__init__.py
zocalo_dls/service/ispybsvc.py
zocalo_dls/wrapper/__init__.py
zocalo_dls/wrapper/dawn.py
zocalo_dls/wrapper/generic.py
zocalo_dls/wrapper/jupyter.py
zocalo_dls/wrapper/papermill.py
zocalo_dls/wrapper/wrapper_utils_dls.py
zocalo_dls-0.4.0.dist-info/LICENSE
zocalo_dls-0.4.0.dist-info/METADATA
zocalo_dls-0.4.0.dist-info/WHEEL
zocalo_dls-0.4.0.dist-info/entry_points.txt
zocalo_dls-0.4.0.dist-info/top_level.txt
zocalo_dls-0.4.0.dist-info/RECORD
