Metadata-Version: 2.1
Name: zocalo-dls
Version: 0.4.0
Summary: Standard components for automated data processing with Zocalo at Diamond Light Source
Home-page: https://github.com/DiamondLightSource/python-zocalo-dls
Author: Diamond Light Source
Author-email: scientificsoftware@diamond.ac.uk
License: BSD license
Keywords: zocalo dls diamond
Classifier: Development Status :: 3 - Alpha
Classifier: Intended Audience :: Developers
Classifier: License :: OSI Approved :: BSD License
Classifier: Natural Language :: English
Classifier: Programming Language :: Python :: 3
Classifier: Programming Language :: Python :: 3.5
Classifier: Programming Language :: Python :: 3.6
Classifier: Programming Language :: Python :: 3.7
License-File: LICENSE
Requires-Dist: ispyb
Requires-Dist: procrunner
Requires-Dist: zocalo
Provides-Extra: jupyter
Requires-Dist: nbformat ; extra == 'jupyter'
Requires-Dist: papermill ; extra == 'jupyter'
